aiomarionette/__init__.py
aiomarionette/py.typed
aiomarionette-0.0.3.dist-info/WHEEL
aiomarionette-0.0.3.dist-info/METADATA
aiomarionette-0.0.3.dist-info/RECORD
