Metadata-Version: 2.1
Name: aiomarionette
Version: 0.0.3
Summary: Firefox Marionette client for asyncio
Home-page: https://github.com/AdmiralNemo/aiomarionette
License: Apache-2.0
Author: Dustin C. Hatch
Author-email: dustin@hatch.name
Requires-Python: >=3.8,<4.0
Classifier: License :: OSI Approved :: Apache Software License
Classifier: Programming Language :: Python :: 3
Classifier: Programming Language :: Python :: 3.10
Classifier: Programming Language :: Python :: 3.8
Classifier: Programming Language :: Python :: 3.9
Project-URL: Repository, https://github.com/AdmiralNemo/aiomarionette
